bcolz/PythonHelper.h
bcolz/__init__.py
bcolz/_version.py
bcolz/arrayprint.py
bcolz/attrs.py
bcolz/carray_ext.cp310-win_amd64.pyd
bcolz/carray_ext.pxd
bcolz/carray_ext.pyx
bcolz/check_blosc_version.h
bcolz/chunked_eval.py
bcolz/ctable.py
bcolz/defaults.py
bcolz/definitions.pxd
bcolz/py2help.py
bcolz/py2help_tests.py
bcolz/toplevel.py
bcolz/utils.py
bcolz/tests/__init__.py
bcolz/tests/all.py
bcolz/tests/common.py
bcolz/tests/test_attrs.py
bcolz/tests/test_carray.py
bcolz/tests/test_carray_objects.py
bcolz/tests/test_ctable.py
bcolz/tests/test_ndcarray.py
bcolz/tests/test_queries.py
bcolz_zipline-1.13.0.dist-info/METADATA
bcolz_zipline-1.13.0.dist-info/WHEEL
bcolz_zipline-1.13.0.dist-info/top_level.txt
bcolz_zipline-1.13.0.dist-info/RECORD
