Metadata-Version: 2.4
Name: bcolz-zipline
Version: 1.13.0
Summary: Columnar and compressed data containers.
Author: Francesc Alted
Author-email: francesc@blosc.org
Maintainer: Stefan Jansen
Maintainer-email: stefan@applied-ai.com
License: Copyright Notice and Statement for bcolz Software Library and Utilities:
Project-URL: repository, https://github.com/stefan-jansen/bcolz-zipline
Classifier: Development Status :: 5 - Production/Stable
Classifier: Intended Audience :: Developers
Classifier: Intended Audience :: Information Technology
Classifier: Intended Audience :: Science/Research
Classifier: License :: OSI Approved :: BSD License
Classifier: Programming Language :: Python
Classifier: Topic :: Software Development :: Libraries :: Python Modules
Classifier: Operating System :: Microsoft :: Windows
Classifier: Operating System :: Unix
Classifier: Programming Language :: Python :: 3
Classifier: Programming Language :: Python :: 3.9
Classifier: Programming Language :: Python :: 3.10
Classifier: Programming Language :: Python :: 3.11
Classifier: Programming Language :: Python :: 3.12
Classifier: Programming Language :: Python :: 3.13
Requires-Python: >=3.9
Requires-Dist: numpy>=1.21
Requires-Dist: packaging
Provides-Extra: optional
Requires-Dist: numexpr>=2.5.2; extra == "optional"
Requires-Dist: dask>=0.9.0; extra == "optional"
Requires-Dist: pandas; extra == "optional"
Requires-Dist: tables; extra == "optional"
Provides-Extra: test
Requires-Dist: tox; extra == "test"
Requires-Dist: pytest>=6.2.3; extra == "test"
Requires-Dist: pytest-cov>=2.11.1; extra == "test"
Requires-Dist: coveralls==3.0.1; extra == "test"
Requires-Dist: pytest-xdist>=2.5.0; extra == "test"
Provides-Extra: dev
Requires-Dist: ruff; extra == "dev"
Requires-Dist: pre-commit>=2.12.1; extra == "dev"
Requires-Dist: Cython>=0.29.21; extra == "dev"
